fragmentshot/__init__.py
fragmentshot/retriever.py
fragmentshot-0.1.5.dist-info/licenses/LICENSE
fragmentshot-0.1.5.dist-info/METADATA
fragmentshot-0.1.5.dist-info/WHEEL
fragmentshot-0.1.5.dist-info/top_level.txt
fragmentshot-0.1.5.dist-info/RECORD
