Metadata-Version: 2.4
Name: fragmentshot
Version: 0.1.5
Summary: Prompt generation for Fragment-Shot and Pivoted Fragment-Shot translation using LLMs
Author-email: Samuel Frontull <samuel.frontull@uibk.ac.at>
License: MIT
Project-URL: Homepage, https://github.com/schtailmuel/fragmentshot
License-File: LICENSE
Dynamic: license-file
